CHANGES.txt
DEPENDENCES.txt
README.txt
setup.py
src/ng/__init__.py
src/ng.app.openid.egg-info/PKG-INFO
src/ng.app.openid.egg-info/SOURCES.txt
src/ng.app.openid.egg-info/dependency_links.txt
src/ng.app.openid.egg-info/namespace_packages.txt
src/ng.app.openid.egg-info/not-zip-safe
src/ng.app.openid.egg-info/requires.txt
src/ng.app.openid.egg-info/top_level.txt
src/ng/app/__init__.py
src/ng/app/openid/__init__.py
src/ng/app/openid/configure.zcml
src/ng/app/openid/cookiecredentials.py
src/ng/app/openid/interfaces.py
src/ng/app/openid/logincredentials.py
src/ng/app/openid/ng.app.openid.txt
src/ng/app/openid/openidauthenticator.py
src/ng/app/openid/openidcredentials.py
src/ng/app/openid/openiderrormessage.py
src/ng/app/openid/openiderrormessageadapter.py
src/ng/app/openid/browser/__init__.py
src/ng/app/openid/browser/configure.zcml
src/ng/app/openid/browser/logout.py
src/ng/app/openid/etc/ng.app.openid-configure.zcml